{
  "type": "alchemistry:dissolver",
  "group": "alchemistry:dissolver",
  "input": {
    "item": "chemlib:ammonium_chloride"
  },
  "output": {
    "groups": [
      {
        "probability": 100.0,
        "results": [
          {
            "item": "chemlib:nitrogen"
          },
          {
            "count": 4,
            "item": "chemlib:hydrogen"
          },
          {
            "item": "chemlib:chlorine"
          }
        ]
      }
    ],
    "rolls": 1,
    "weighted": false
  }
}